README.md
setup.py
reinvent_hitl/__init__.py
reinvent_hitl/input.py
reinvent_hitl/main_test.py
reinvent_hitl.egg-info/PKG-INFO
reinvent_hitl.egg-info/SOURCES.txt
reinvent_hitl.egg-info/dependency_links.txt
reinvent_hitl.egg-info/top_level.txt
reinvent_hitl/running_modes/__init__.py
reinvent_hitl/running_modes/manager.py
reinvent_hitl/running_modes/automated_curriculum_learning/__init__.py
reinvent_hitl/running_modes/automated_curriculum_learning/automated_curriculum_runner.py
reinvent_hitl/running_modes/automated_curriculum_learning/actions/__init__.py
reinvent_hitl/running_modes/automated_curriculum_learning/actions/base_action.py
reinvent_hitl/running_modes/automated_curriculum_learning/actions/base_sample_action.py
reinvent_hitl/running_modes/automated_curriculum_learning/actions/lib_invent_sample_model.py
reinvent_hitl/running_modes/automated_curriculum_learning/actions/link_invent_sample_model.py
reinvent_hitl/running_modes/automated_curriculum_learning/actions/reinvent_sample_model.py
reinvent_hitl/running_modes/automated_curriculum_learning/curriculum_strategy/__init__.py
reinvent_hitl/running_modes/automated_curriculum_learning/curriculum_strategy/base_curriculum_strategy.py
reinvent_hitl/running_modes/automated_curriculum_learning/curriculum_strategy/curriculum_strategy.py
reinvent_hitl/running_modes/automated_curriculum_learning/curriculum_strategy/linkinvent_curriculum_strategy.py
reinvent_hitl/running_modes/automated_curriculum_learning/curriculum_strategy/no_curriculum_strategy.py
reinvent_hitl/running_modes/automated_curriculum_learning/curriculum_strategy/reinvent_curriculum_strategy.py
reinvent_hitl/running_modes/automated_curriculum_learning/dto/__init__.py
reinvent_hitl/running_modes/automated_curriculum_learning/dto/curriculum_outcome_dto.py
reinvent_hitl/running_modes/automated_curriculum_learning/dto/sampled_batch_dto.py
reinvent_hitl/running_modes/automated_curriculum_learning/dto/sampled_sequences_dto.py
reinvent_hitl/running_modes/automated_curriculum_learning/dto/timestep_dto.py
reinvent_hitl/running_modes/automated_curriculum_learning/dto/updated_likelihoods_dto.py
